intentify/__init__.py
intentify/main.py
intentify-0.0.3.dist-info/METADATA
intentify-0.0.3.dist-info/WHEEL
intentify-0.0.3.dist-info/top_level.txt
intentify-0.0.3.dist-info/RECORD
